{
	"info": {
		"_postman_id": "d5c6b0d6-bfef-4acf-bae1-6a305c89b7ab",
		"name": "Test Explore With Me - feature-location",
		"schema": "https://schema.getpostman.com/json/collection/v2.1.0/collection.json",
		"_exporter_id": "37774119"
	},
	"item": [
		{
			"name": "Validation",
			"item": [
				{
					"name": "Location",
					"item": [
						{
							"name": "Unrequired query params",
							"item": [
								{
									"name": "Поиск локаций без нескольких Query params",
									"event": [
										{
											"listen": "prerequest",
											"script": {
												"exec": [
													"const main = async () => {\r",
													"    const api = new API(pm);\r",
													"    const rnd = new RandomUtils();\r",
													"\r",
													"    try {\r",
													"        const venue = await api.addVenue(rnd.getVenue());\r",
													"        pm.collectionVariables.set(\"vid\", venue.id)\r",
													"    } catch(err) {\r",
													"        console.error(\"Ошибка при подготовке тестовых данных.\", err);\r",
													"    }\r",
													"};\r",
													"\r",
													"const interval = setInterval(() => {}, 1000);\r",
													"\r",
													"setTimeout(async () => \r",
													"    {\r",
													"        try {\r",
													"            await main();\r",
													"        } catch (e) {\r",
													"            console.error(e);\r",
													"        } finally {\r",
													"            clearInterval(interval);\r",
													"        }\r",
													"    },  \r",
													"    100 \r",
													");"
												],
												"type": "text/javascript",
												"packages": {}
											}
										},
										{
											"listen": "test",
											"script": {
												"exec": [
													"pm.test(\"Ответ должен содержать код статуса 200 и данные в формате json\", function () {\r",
													"    pm.response.to.be.ok;    \r",
													"    pm.response.to.be.withBody;\r",
													"    pm.response.to.be.json;\r",
													"});"
												],
												"type": "text/javascript",
												"packages": {}
											}
										}
									],
									"request": {
										"method": "GET",
										"header": [
											{
												"key": "Accept",
												"value": "application/json"
											}
										],
										"url": {
											"raw": "{{baseUrl}}/admin/venues?ids={{vid}}",
											"host": [
												"{{baseUrl}}"
											],
											"path": [
												"admin",
												"venues"
											],
											"query": [
												{
													"key": "from",
													"value": "0",
													"description": "количество элементов, которые нужно пропустить для формирования текущего набора",
													"disabled": true
												},
												{
													"key": "size",
													"value": "10",
													"description": "количество элементов в наборе",
													"disabled": true
												},
												{
													"key": "ids",
													"value": "{{vid}}"
												}
											]
										}
									},
									"response": []
								},
								{
									"name": "Поиск локаций без параметра ids",
									"event": [
										{
											"listen": "prerequest",
											"script": {
												"exec": [
													"const main = async () => {\r",
													"    const api = new API(pm);\r",
													"    const rnd = new RandomUtils();\r",
													"\r",
													"    let compilation;\r",
													"    try {\r",
													"        let venue1 = rnd.getVenue();\r",
													"        venue1 = await api.addVenue(venue1);\r",
													"\r",
													"        let venue2 = rnd.getVenue()\r",
													"        venue2 = await api.addVenue(venue2);\r",
													"       \r",
													"        pm.collectionVariables.set('source1', venue1);\r",
													"        pm.collectionVariables.set('source2', venue2);\r",
													"\r",
													"    } catch(err) {\r",
													"        console.error(\"Ошибка при подготовке тестовых данных.\", err);\r",
													"    }\r",
													"};\r",
													"\r",
													"const interval = setInterval(() => {}, 1000);\r",
													"\r",
													"setTimeout(async () => \r",
													"    {\r",
													"        try {\r",
													"            await main();\r",
													"        } catch (e) {\r",
													"            console.error(e);\r",
													"        } finally {\r",
													"            clearInterval(interval);\r",
													"        }\r",
													"    },  \r",
													"    100 \r",
													");"
												],
												"type": "text/javascript",
												"packages": {}
											}
										},
										{
											"listen": "test",
											"script": {
												"exec": [
													"pm.test(\"Ответ должен содержать код статуса 200 и данные в формате json\", function () {\r",
													"    pm.response.to.be.ok;    \r",
													"    pm.response.to.be.withBody;\r",
													"    pm.response.to.be.json;\r",
													"});\r",
													"\r",
													"const target = pm.response.json();\r",
													"const source1 = pm.collectionVariables.get('source1');\r",
													"const source2 = pm.collectionVariables.get('source2');\r",
													"\r",
													"pm.test(\"Локации должны содержать поля: id, name, location\", function () {\r",
													"    pm.expect(target[target.length-2]).to.have.property('id');\r",
													"    pm.expect(target[target.length-2]).to.have.property('name');\r",
													"    pm.expect(target[target.length-2]).to.have.property('location');\r",
													"});\r",
													"\r",
													"pm.test(\"Данные последних двух локаций должны совпадать с данными добавленных локаций\", function () {\r",
													"    pm.expect(target[target.length-2].id).to.equal(source1.id);\r",
													"    pm.expect(target[target.length-2].name).to.equal(source1.name);\r",
													"    pm.expect(target[target.length-2].location.lat).to.equal(source1.location.lat);\r",
													"    pm.expect(target[target.length-2].location.lon).to.equal(source1.location.lon);\r",
													"    pm.expect(target[target.length-1].id).to.equal(source2.id);\r",
													"    pm.expect(target[target.length-1].name).to.equal(source2.name);\r",
													"    pm.expect(target[target.length-1].location.lat).to.equal(source2.location.lat);\r",
													"    pm.expect(target[target.length-1].location.lon).to.equal(source2.location.lon);\r",
													"});\r",
													""
												],
												"type": "text/javascript",
												"packages": {}
											}
										}
									],
									"request": {
										"method": "GET",
										"header": [
											{
												"key": "Accept",
												"value": "application/json"
											}
										],
										"url": {
											"raw": "{{baseUrl}}/admin/venues?from={{fromId}}&size=100000",
											"host": [
												"{{baseUrl}}"
											],
											"path": [
												"admin",
												"venues"
											],
											"query": [
												{
													"key": "ids",
													"value": "{{uid}}",
													"description": "id пользователей",
													"disabled": true
												},
												{
													"key": "from",
													"value": "{{fromId}}",
													"description": "количество элементов, которые нужно пропустить для формирования текущего набора"
												},
												{
													"key": "size",
													"value": "100000",
													"description": "количество элементов в наборе"
												}
											]
										}
									},
									"response": []
								}
							]
						},
						{
							"name": "Required params in body",
							"item": [
								{
									"name": "Добавление локации с наименование состоящим только из пробелов",
									"event": [
										{
											"listen": "prerequest",
											"script": {
												"exec": [
													"const main = async () => {\r",
													"    const api = new API(pm);\r",
													"    const rnd = new RandomUtils();\r",
													"\r",
													"    let venue;\r",
													"    try {\r",
													"        venue = rnd.getVenue();\r",
													"        venue.name = \"       \";\r",
													"    } catch(err) {\r",
													"        console.error(\"Ошибка при подготовке тестовых данных.\", err);\r",
													"    }\r",
													"\r",
													"    pm.request.body.update({\r",
													"        mode: 'raw',\r",
													"        raw: JSON.stringify(venue),\r",
													"        options: { raw: { language: 'json' } }\r",
													"    });\r",
													"};\r",
													"\r",
													"const interval = setInterval(() => {}, 1000);\r",
													"\r",
													"setTimeout(async () => \r",
													"    {\r",
													"        try {\r",
													"            await main();\r",
													"        } catch (e) {\r",
													"            console.error(e);\r",
													"        } finally {\r",
													"            clearInterval(interval);\r",
													"        }\r",
													"    },  \r",
													"    100 \r",
													");"
												],
												"type": "text/javascript",
												"packages": {}
											}
										},
										{
											"listen": "test",
											"script": {
												"exec": [
													"pm.test(\"Ответ должен содержать код статуса 400\", function () {\r",
													"    pm.response.to.have.status(400);\r",
													"});"
												],
												"type": "text/javascript",
												"packages": {}
											}
										}
									],
									"request": {
										"method": "POST",
										"header": [
											{
												"key": "Content-Type",
												"value": "application/json"
											},
											{
												"key": "Accept",
												"value": "application/json"
											}
										],
										"body": {
											"mode": "raw",
											"raw": "{{request_body}}",
											"options": {
												"raw": {
													"language": "json"
												}
											}
										},
										"url": {
											"raw": "{{baseUrl}}/admin/venues",
											"host": [
												"{{baseUrl}}"
											],
											"path": [
												"admin",
												"venues"
											]
										}
									},
									"response": []
								},
								{
									"name": "Добавление локации без поля name",
									"event": [
										{
											"listen": "prerequest",
											"script": {
												"exec": [
													"const main = async () => {\r",
													"    const api = new API(pm);\r",
													"    const rnd = new RandomUtils();\r",
													"\r",
													"    let venue;\r",
													"    try {\r",
													"        venue = rnd.getVenue();\r",
													"        delete venue.name;\r",
													"    } catch(err) {\r",
													"        console.error(\"Ошибка при подготовке тестовых данных.\", err);\r",
													"    }\r",
													"\r",
													"    pm.request.body.update({\r",
													"        mode: 'raw',\r",
													"        raw: JSON.stringify(venue),\r",
													"        options: { raw: { language: 'json' } }\r",
													"    });\r",
													"};\r",
													"\r",
													"const interval = setInterval(() => {}, 1000);\r",
													"\r",
													"setTimeout(async () => \r",
													"    {\r",
													"        try {\r",
													"            await main();\r",
													"        } catch (e) {\r",
													"            console.error(e);\r",
													"        } finally {\r",
													"            clearInterval(interval);\r",
													"        }\r",
													"    },  \r",
													"    100 \r",
													");"
												],
												"type": "text/javascript",
												"packages": {}
											}
										},
										{
											"listen": "test",
											"script": {
												"exec": [
													"pm.test(\"Ответ должен содержать код статуса 400\", function () {\r",
													"    pm.response.to.have.status(400);\r",
													"});"
												],
												"type": "text/javascript",
												"packages": {}
											}
										}
									],
									"request": {
										"method": "POST",
										"header": [
											{
												"key": "Content-Type",
												"value": "application/json"
											},
											{
												"key": "Accept",
												"value": "application/json"
											}
										],
										"body": {
											"mode": "raw",
											"raw": "{{request_body}}",
											"options": {
												"raw": {
													"language": "json"
												}
											}
										},
										"url": {
											"raw": "{{baseUrl}}/admin/venues",
											"host": [
												"{{baseUrl}}"
											],
											"path": [
												"admin",
												"venues"
											]
										}
									},
									"response": []
								},
								{
									"name": "Добавление локации без поля location",
									"event": [
										{
											"listen": "prerequest",
											"script": {
												"exec": [
													"const main = async () => {\r",
													"    const api = new API(pm);\r",
													"    const rnd = new RandomUtils();\r",
													"\r",
													"   let venue;\r",
													"    try {\r",
													"        venue = rnd.getVenue();\r",
													"        delete venue.location;\r",
													"    } catch(err) {\r",
													"        console.error(\"Ошибка при подготовке тестовых данных.\", err);\r",
													"    }\r",
													"\r",
													"    pm.request.body.update({\r",
													"        mode: 'raw',\r",
													"        raw: JSON.stringify(venue),\r",
													"        options: { raw: { language: 'json' } }\r",
													"    });\r",
													"};\r",
													"\r",
													"const interval = setInterval(() => {}, 1000);\r",
													"\r",
													"setTimeout(async () => \r",
													"    {\r",
													"        try {\r",
													"            await main();\r",
													"        } catch (e) {\r",
													"            console.error(e);\r",
													"        } finally {\r",
													"            clearInterval(interval);\r",
													"        }\r",
													"    },  \r",
													"    100 \r",
													");"
												],
												"type": "text/javascript",
												"packages": {}
											}
										},
										{
											"listen": "test",
											"script": {
												"exec": [
													"pm.test(\"Ответ должен содержать код статуса 400\", function () {\r",
													"    pm.response.to.have.status(400);\r",
													"});"
												],
												"type": "text/javascript",
												"packages": {}
											}
										}
									],
									"request": {
										"method": "POST",
										"header": [
											{
												"key": "Content-Type",
												"value": "application/json"
											},
											{
												"key": "Accept",
												"value": "application/json"
											}
										],
										"body": {
											"mode": "raw",
											"raw": "{{request_body}}",
											"options": {
												"raw": {
													"language": "json"
												}
											}
										},
										"url": {
											"raw": "{{baseUrl}}/admin/venues",
											"host": [
												"{{baseUrl}}"
											],
											"path": [
												"admin",
												"venues"
											]
										}
									},
									"response": []
								}
							]
						}
					]
				}
			]
		},
		{
			"name": "Location",
			"item": [
				{
					"name": "Удаление локации",
					"event": [
						{
							"listen": "prerequest",
							"script": {
								"exec": [
									"const main = async () => {\r",
									"    const api = new API(pm);\r",
									"    const rnd = new RandomUtils();\r",
									"\r",
									"    try {\r",
									"        const venue = await api.addVenue(rnd.getVenue());\r",
									"        const findedVenue = await api.findVenue(venue.id);\r",
									"        pm.collectionVariables.set(\"vid\", venue.id)\r",
									"        pm.collectionVariables.set(\"response\", findedVenue)\r",
									"    } catch(err) {\r",
									"        console.error(\"Ошибка при подготовке тестовых данных.\", err);\r",
									"    }\r",
									"};\r",
									"\r",
									"const interval = setInterval(() => {}, 1000);\r",
									"\r",
									"setTimeout(async () => \r",
									"    {\r",
									"        try {\r",
									"            await main();\r",
									"        } catch (e) {\r",
									"            console.error(e);\r",
									"        } finally {\r",
									"            clearInterval(interval);\r",
									"        }\r",
									"    },  \r",
									"    100 \r",
									");"
								],
								"type": "text/javascript",
								"packages": {}
							}
						},
						{
							"listen": "test",
							"script": {
								"exec": [
									"pm.test(\"Ответ должен содержать код статуса 204\", function () {\r",
									"    pm.response.to.have.status(204);\r",
									"});\r",
									"const source = pm.collectionVariables.get('response');\r",
									"const venueId = pm.collectionVariables.get('vid');\r",
									"\r",
									"pm.test(\"Локация должна быть найдена до выполнения запроса\", function(){\r",
									"    pm.expect(source.length).to.eql(1);\r",
									"    pm.expect(source[0].id).to.eql(venueId);\r",
									"});\r",
									"let body\r",
									"const req = {\r",
									"                url: pm.collectionVariables.get(\"baseUrl\") + \"/admin/venues?ids=\" + venueId,\r",
									"                method: \"GET\",\r",
									"                body: body == null ? \"\" : JSON.stringify(body),\r",
									"                header: { \"Content-Type\": \"application/json\" },\r",
									"            };\r",
									"pm.sendRequest(req, (error, response) => {\r",
									"    pm.test(\"Локация должна быть удалена после выполнения запроса\", function(){\r",
									"        pm.expect(response.json().length).to.eql(0);\r",
									"    });\r",
									"})"
								],
								"type": "text/javascript",
								"packages": {}
							}
						}
					],
					"request": {
						"method": "DELETE",
						"header": [
							{
								"key": "Accept",
								"value": "application/json"
							}
						],
						"url": {
							"raw": "{{baseUrl}}/admin/venues/:venueId",
							"host": [
								"{{baseUrl}}"
							],
							"path": [
								"admin",
								"venues",
								":venueId"
							],
							"variable": [
								{
									"key": "venueId",
									"value": "{{vid}}"
								}
							]
						},
						"description": "Обратите внимание: с категорий не должно быть связано ни одного события."
					},
					"response": []
				},
				{
					"name": "Добавление локации",
					"event": [
						{
							"listen": "prerequest",
							"script": {
								"exec": [
									"const main = async () => {\r",
									"    const api = new API(pm);\r",
									"    const rnd = new RandomUtils();\r",
									"\r",
									"    let venue;\r",
									"    try {\r",
									"        venue = rnd.getVenue();\r",
									"    } catch(err) {\r",
									"        console.error(\"Ошибка при подготовке тестовых данных.\", err);\r",
									"    }\r",
									"\r",
									"    pm.request.body.update({\r",
									"        mode: 'raw',\r",
									"        raw: JSON.stringify(venue),\r",
									"        options: { raw: { language: 'json' } }\r",
									"    });\r",
									"};\r",
									"\r",
									"const interval = setInterval(() => {}, 1000);\r",
									"\r",
									"setTimeout(async () => \r",
									"    {\r",
									"        try {\r",
									"            await main();\r",
									"        } catch (e) {\r",
									"            console.error(e);\r",
									"        } finally {\r",
									"            clearInterval(interval);\r",
									"        }\r",
									"    },  \r",
									"    100 \r",
									");"
								],
								"type": "text/javascript",
								"packages": {}
							}
						},
						{
							"listen": "test",
							"script": {
								"exec": [
									"pm.test(\"Ответ должен содержать код статуса 201 и данные в формате json\", function () {\r",
									"    pm.response.to.have.status(201);\r",
									"    pm.response.to.be.withBody;\r",
									"    pm.response.to.be.json;\r",
									"});\r",
									"\r",
									"const source = JSON.parse(pm.request.body.raw);\r",
									"const target = pm.response.json();\r",
									"\r",
									"pm.test(\"Пользователь должен содержать поля: id, name, location\", function () {\r",
									"pm.expect(target).to.have.property('id');\r",
									"pm.expect(target).to.have.property('name');\r",
									"pm.expect(target).to.have.property('location');\r",
									"});\r",
									"\r",
									"pm.test(\"Данные в ответе должны соответствовать данным в запросе\", function () {\r",
									"    pm.expect(target.id).to.not.be.null;\r",
									"    pm.expect(source.name).equal(target.name, 'Имя локации должно соответствовать отправленному в запросе');\r",
									"    pm.expect(source.location.lat).equal(target.location.lat, 'Поле lat должНо соответствовать отправленному в запросе');\r",
									"     pm.expect(source.location.lon).equal(target.location.lon, 'Поле lon должНо соответствовать отправленному в запросе');\r",
									"});"
								],
								"type": "text/javascript",
								"packages": {}
							}
						}
					],
					"request": {
						"method": "POST",
						"header": [
							{
								"key": "Content-Type",
								"value": "application/json"
							},
							{
								"key": "Accept",
								"value": "application/json"
							}
						],
						"body": {
							"mode": "raw",
							"raw": "{{request_body}}",
							"options": {
								"raw": {
									"language": "json"
								}
							}
						},
						"url": {
							"raw": "{{baseUrl}}/admin/venues",
							"host": [
								"{{baseUrl}}"
							],
							"path": [
								"admin",
								"venues"
							]
						}
					},
					"response": []
				},
				{
					"name": "Изменение локации",
					"event": [
						{
							"listen": "prerequest",
							"script": {
								"exec": [
									"const main = async () => {\r",
									"    const api = new API(pm);\r",
									"    const rnd = new RandomUtils();\r",
									"    let venue\r",
									"    try {\r",
									"        venue = await api.addVenue(rnd.getVenue());\r",
									"    } catch(err) {\r",
									"        console.error(\"Ошибка при подготовке тестовых данных.\", err);\r",
									"    }\r",
									"    pm.collectionVariables.set(\"vid\", Number(venue.id))\r",
									"    updVenue = rnd.getVenue();\r",
									"    pm.request.body.update({\r",
									"        mode: 'raw',\r",
									"        raw: JSON.stringify({\r",
									"            name : updVenue.name\r",
									"        }),\r",
									"        options: { raw: { language: 'json' } }\r",
									"    });\r",
									"};\r",
									"\r",
									"const interval = setInterval(() => {}, 1000);\r",
									"\r",
									"setTimeout(async () => \r",
									"    {\r",
									"        try {\r",
									"            await main();\r",
									"        } catch (e) {\r",
									"            console.error(e);\r",
									"        } finally {\r",
									"            clearInterval(interval);\r",
									"        }\r",
									"    },  \r",
									"    100 \r",
									");"
								],
								"type": "text/javascript",
								"packages": {}
							}
						},
						{
							"listen": "test",
							"script": {
								"exec": [
									"pm.test(\"Ответ должен содержать код статуса 200 и данные в формате json\", function () {\r",
									"    pm.response.to.be.ok;    \r",
									"    pm.response.to.be.withBody;\r",
									"    pm.response.to.be.json;\r",
									"});\r",
									"\r",
									"const source = JSON.parse(pm.request.body.raw);\r",
									"const target = pm.response.json();\r",
									"\r",
									"pm.test(\"Локация должна содержать поля: id, name, location\", function () {\r",
									"pm.expect(target).to.have.property('id');\r",
									"pm.expect(target).to.have.property('name');\r",
									"pm.expect(target).to.have.property('location');\r",
									"});\r",
									"\r",
									"pm.test(\"Данные в ответе должны соответствовать данным в запросе\", function () {\r",
									"    pm.expect(target.id).to.not.be.null;\r",
									"    pm.expect(source.name).equal(target.name, 'Название локации должно совпадать с отправленным');\r",
									"});"
								],
								"type": "text/javascript",
								"packages": {}
							}
						}
					],
					"request": {
						"method": "PATCH",
						"header": [],
						"body": {
							"mode": "raw",
							"raw": "{{request_body}}"
						},
						"url": {
							"raw": "{{baseUrl}}/admin/venues/:vid",
							"host": [
								"{{baseUrl}}"
							],
							"path": [
								"admin",
								"venues",
								":vid"
							],
							"variable": [
								{
									"key": "vid",
									"value": "{{vid}}"
								}
							]
						}
					},
					"response": []
				}
			]
		},
		{
			"name": "Event",
			"item": [
				{
					"name": "Поиск событий по локации",
					"event": [
						{
							"listen": "prerequest",
							"script": {
								"exec": [
									"const main = async () => {\r",
									"    const api = new API(pm);\r",
									"    const rnd = new RandomUtils();\r",
									"   let venue;\r",
									"    try {\r",
									"        venue = rnd.getVenue();\r",
									"        venue.location.lat = 59.940910;\r",
									"        venue.location.lon = 30.312941;\r",
									"        venue.name = \"зимний дворец\";\r",
									"        const venue1 = await api.addVenue(venue);\r",
									"    \r",
									"        venue.location.lat = 59.925867;\r",
									"        venue.location.lon = 30.296088;\r",
									"        venue.name = \"мариинский театр\";\r",
									"        const venue2 = await api.addVenue(venue);\r",
									"        \r",
									"        const user = await api.addUser(rnd.getUser());\r",
									"        const category = await api.addCategory(rnd.getCategory());\r",
									"        \r",
									"        let event1 = await api.addEvent(user.id, rnd.getEvent(category.id));\r",
									"        event1 = await api.updateEvent(event1.id, {venue: venue1.id, eventDate: rnd.getFutureDateTime(5)});\r",
									"       \r",
									"        let event2 = await api.addEvent(user.id, rnd.getEvent(category.id));\r",
									"        event2 = await api.updateEvent(event2.id, {venue: venue2.id, eventDate: rnd.getFutureDateTime(6)});\r",
									"\r",
									"        let event3 = await api.addEvent(user.id, rnd.getEvent(category.id));\r",
									"        event3 = await api.updateEvent(event3.id, {location: {lat: 59.939324, lon: 30.316661},\r",
									"        eventDate: rnd.getFutureDateTime(7)});\r",
									"\r",
									"       pm.request.removeQueryParams(['venue']);\r",
									"        pm.request.addQueryParams(['venue=' + venue1.id, 'users=' + user.id]);\r",
									"        pm.collectionVariables.set('response', [event1, event3]);\r",
									"    } catch(err) {\r",
									"        console.error(\"Ошибка при подготовке тестовых данных.\", err);\r",
									"    }\r",
									"};\r",
									"\r",
									"const interval = setInterval(() => {}, 1000);\r",
									"\r",
									"setTimeout(async () => \r",
									"    {\r",
									"        try {\r",
									"            // выполняем наш скрипт\r",
									"            await main();\r",
									"        } catch (e) {\r",
									"            console.error(e);\r",
									"        } finally {\r",
									"            clearInterval(interval);\r",
									"        }\r",
									"    },  \r",
									"    100 \r",
									");"
								],
								"type": "text/javascript",
								"packages": {}
							}
						},
						{
							"listen": "test",
							"script": {
								"exec": [
									"pm.test(\"Ответ должен содержать код статуса 200 и данные в формате json\", function () {\r",
									"    pm.response.to.be.ok;    \r",
									"    pm.response.to.be.withBody;\r",
									"    pm.response.to.be.json;\r",
									"});\r",
									"\r",
									"const source = pm.collectionVariables.get('response');\r",
									"\r",
									"\r",
									"pm.test(\"Должно быть найдено 2 локации по заданному фильтру\", function () {\r",
									"    pm.expect(pm.response.json().length).to.eql(2);\r",
									"});\r",
									"\r",
									"const target = pm.response.json();\r",
									"\r",
									"pm.test(\"Событие должно содержать поля: id, title, annotation, category, paid, eventDate, initiator, views, confirmedRequests, description, participantLimit, state, createdOn, publishedOn, location, requestModeration, venue\", function () {\r",
									"pm.expect(target[0]).to.have.property('id');\r",
									"pm.expect(target[0]).to.have.property('title');\r",
									"pm.expect(target[0]).to.have.property('annotation');\r",
									"pm.expect(target[0]).to.have.property('category');\r",
									"pm.expect(target[0]).to.have.property('paid');\r",
									"pm.expect(target[0]).to.have.property('eventDate');\r",
									"pm.expect(target[0]).to.have.property('initiator');\r",
									"pm.expect(target[0]).to.have.property('views');\r",
									"pm.expect(target[0]).to.have.property('confirmedRequests');\r",
									"pm.expect(target[0]).to.have.property('description');\r",
									"pm.expect(target[0]).to.have.property('participantLimit');\r",
									"pm.expect(target[0]).to.have.property('state');\r",
									"pm.expect(target[0]).to.have.property('createdOn');\r",
									"pm.expect(target[0]).to.have.property('publishedOn');\r",
									"pm.expect(target[0]).to.have.property('location');\r",
									"pm.expect(target[0]).to.have.property('requestModeration');\r",
									"pm.expect(target[0]).to.have.property('venue');\r",
									"});\r",
									"\r",
									"\r",
									"\r",
									"pm.test(\"Данные в ответе должны соответствовать данным в запросе\", function () {\r",
									"    pm.expect(source[0].location.lat).equal(target[0].location.lat, 'Широта события должна соответствовать искомому событию');\r",
									"    pm.expect(source[0].location.lon).equal(target[0].location.lon, 'Долгота события должна соответствовать искомому событию');\r",
									"    pm.expect(source[1].location.lat).equal(target[1].location.lat, 'Широта события должна соответствовать искомому событию');\r",
									"    pm.expect(source[1].location.lon).equal(target[1].location.lon, 'Долгота события должна соответствовать искомому событию');\r",
									"   \r",
									"});"
								],
								"type": "text/javascript",
								"packages": {}
							}
						}
					],
					"request": {
						"method": "GET",
						"header": [
							{
								"key": "Accept",
								"value": "application/json"
							}
						],
						"url": {
							"raw": "{{baseUrl}}/admin/events?venue=0&radius=1&rangeStart=2022-01-06%2013%3A30%3A38&rangeEnd=2097-09-06%2013%3A30%3A38&from=0&size=1000",
							"host": [
								"{{baseUrl}}"
							],
							"path": [
								"admin",
								"events"
							],
							"query": [
								{
									"key": "venue",
									"value": "0"
								},
								{
									"key": "radius",
									"value": "1"
								},
								{
									"key": "rangeStart",
									"value": "2022-01-06%2013%3A30%3A38",
									"description": "дата и время не раньше которых должно произойти событие"
								},
								{
									"key": "rangeEnd",
									"value": "2097-09-06%2013%3A30%3A38",
									"description": "дата и время не позже которых должно произойти событие"
								},
								{
									"key": "from",
									"value": "0",
									"description": "количество событий, которые нужно пропустить для формирования текущего набора"
								},
								{
									"key": "size",
									"value": "1000",
									"description": "количество событий в наборе"
								}
							]
						},
						"description": "Эндпоинт возвращает полную информацию обо всех событиях подходящих под переданные условия"
					},
					"response": []
				}
			]
		}
	],
	"event": [
		{
			"listen": "prerequest",
			"script": {
				"type": "text/javascript",
				"exec": [
					"API = class {",
					"    constructor(postman, verbose = false, baseUrl = \"http://localhost:8080\") {",
					"        this.baseUrl = baseUrl;",
					"        this.pm = postman;",
					"        this._verbose = verbose;",
					"    }",
					"",
					"    async addUser(user, verbose=null) {",
					"        return this.post(\"/admin/users\", user, \"Ошибка при добавлении нового пользователя: \", verbose);",
					"    }",
					"",
					"    async addCategory(category, verbose=null) {",
					"        return this.post(\"/admin/categories\", category, \"Ошибка при добавлении новой категории: \", verbose);",
					"    }",
					"",
					"    async addVenue(venue, verbose=null) {",
					"        return this.post(\"/admin/venues\", venue, \"Ошибка при добавлении места проведения: \", verbose);",
					"    }",
					"",
					"    async addEvent(userId, event, verbose=null) {",
					"        return this.post(\"/users/\" + userId + \"/events\", event, \"Ошибка при добавлении нового события: \", verbose);",
					"    }",
					"",
					"    async updateEvent(eventId, event, verbose=null) {",
					"        return this.patch(\"/admin/events/\" + eventId, event, \"Ошибка при обновлении  события: \", verbose);",
					"    }",
					"",
					"    async findCategory(catId, verbose=null) {",
					"        return this.get('/categories/' + catId, null, \"Ошибка при поиске категории по id\", verbose);",
					"    }",
					"",
					"    async findEvent(eventId, verbose=null) {",
					"        return this.get('/events/' + eventId, null, \"Ошибка при поиске события по id\", verbose);",
					"    }",
					"",
					"    async findUser(userId, verbose=null) {",
					"        return this.get('/admin/users?ids=' + userId, null, \"Ошибка при поиске пользователя по id\", verbose);",
					"    }",
					"",
					"    async findVenue(venueId, verbose=null) {",
					"        return this.get('/admin/venues?ids=' + venueId, null, \"Ошибка при поиске локации по id\", verbose);",
					"    }",
					"",
					"    async post(path, body, errorText = \"Ошибка при выполнении post-запроса: \", verbose=null) {",
					"        return this.sendRequest(\"POST\", path, body, errorText, verbose);",
					"    }",
					"",
					"    async patch(path, body = null, errorText = \"Ошибка при выполнении patch-запроса: \", verbose=null) {",
					"        return this.sendRequest(\"PATCH\", path, body, errorText, verbose);",
					"    }",
					"",
					"    async get(path, body = null, errorText = \"Ошибка при выполнении get-запроса: \", verbose=null) {",
					"        return this.sendRequest(\"GET\", path, body, errorText, verbose);",
					"    }",
					"    async sendRequest(method, path, body=null, errorText = \"Ошибка при выполнении запроса: \", verbose=null) {",
					"        return new Promise((resolve, reject) => {",
					"            verbose = verbose == null ? this._verbose : verbose;",
					"            const request = {",
					"                url: this.baseUrl + path,",
					"                method: method,",
					"                body: body == null ? \"\" : JSON.stringify(body),",
					"                header: { \"Content-Type\": \"application/json\" },",
					"            };",
					"            if(verbose) {",
					"                console.log(\"Отправляю запрос: \", request);",
					"            }",
					"",
					"            try {",
					"                this.pm.sendRequest(request, (error, response) => {",
					"                    if(error || (response.code >= 400 && response.code <= 599)) {",
					"                        let err = error ? error : JSON.stringify(response.json());",
					"                        console.error(\"При выполнении запроса к серверу возникла ошика.\\n\", err,",
					"                             \"\\nДля отладки проблемы повторите такой же запрос к вашей программе \" + ",
					"                             \"на локальном компьютере. Данные запроса:\\n\", JSON.stringify(request));",
					"",
					"                        reject(new Error(errorText + err));",
					"                    }",
					"                    if(verbose) {",
					"                        console.log(\"Результат обработки запроса: код состояния - \", response.code, \", тело: \", response.json());",
					"                    }",
					"                    if (response.stream.length === 0){",
					"                        reject(new Error('Отправлено пустое тело ответа'))",
					"                    }else{",
					"                        resolve(response.json());",
					"                    }",
					"                });",
					"                ",
					"            } catch(err) {",
					"                if(verbose) {",
					"                    console.error(errorText, err);",
					"                }",
					"                return Promise.reject(err);",
					"            }",
					"        });",
					"    }",
					"};",
					"",
					"RandomUtils = class {",
					"    constructor() {}",
					"",
					"    getUser() {",
					"        return {",
					"            name: pm.variables.replaceIn('{{$randomFullName}}'),",
					"            email: pm.variables.replaceIn('{{$randomEmail}}')",
					"        };",
					"    }",
					"",
					"    getCategory() {",
					"        return {",
					"            name: pm.variables.replaceIn('{{$randomWord}}') + Math.floor(Math.random() * 10000 * Math.random()).toString()",
					"        };",
					"    }",
					"",
					"    getVenue() {",
					"        return {",
					"            name: pm.variables.replaceIn('{{$randomWord}}') + Math.floor(Math.random() * 10 * Math.random()).toString(),",
					"            location: {",
					"                lat: parseFloat(pm.variables.replaceIn('{{$randomLatitude}}')),",
					"                lon: parseFloat(pm.variables.replaceIn('{{$randomLongitude}}'))",
					"            }",
					"        }",
					"    }",
					"",
					"    getEvent(categoryId) {",
					"        return {",
					"            annotation: pm.variables.replaceIn('{{$randomLoremParagraph}}'),",
					"            category: categoryId,",
					"            description: pm.variables.replaceIn('{{$randomLoremParagraphs}}'),",
					"            eventDate: this.getFutureDateTime(),",
					"            location: {",
					"                lat: parseFloat(pm.variables.replaceIn('{{$randomLatitude}}')),",
					"                lon: parseFloat(pm.variables.replaceIn('{{$randomLongitude}}')),",
					"            },",
					"            paid: pm.variables.replaceIn('{{$randomBoolean}}'),",
					"            participantLimit: pm.variables.replaceIn('{{$randomInt}}'),",
					"            requestModeration: pm.variables.replaceIn('{{$randomBoolean}}'),",
					"            title: pm.variables.replaceIn('{{$randomLoremSentence}}'),",
					"        }",
					"    }",
					"",
					"",
					"    getFutureDateTime(hourShift = 5, minuteShift=0, yearShift=0) {",
					"        let moment = require('moment');",
					"",
					"        let m = moment();",
					"        m.add(hourShift, 'hour');",
					"        m.add(minuteShift, 'minute');",
					"        m.add(yearShift, 'year');",
					"",
					"        return m.format('YYYY-MM-DD HH:mm:ss');",
					"    }",
					"",
					"    getWord(length = 1) {",
					"        let result = '';",
					"        const characters = 'ABCDEFGHIJKLMNOPQRSTUVWXYZabcdefghijklmnopqrstuvwxyz0123456789';",
					"        const charactersLength = characters.length;",
					"        let counter = 0;",
					"        while (counter < length) {",
					"            result += characters.charAt(Math.floor(Math.random() * charactersLength));",
					"            counter += 1;",
					"        }",
					"        return result;",
					"    }",
					"}"
				]
			}
		},
		{
			"listen": "test",
			"script": {
				"type": "text/javascript",
				"exec": [
					""
				]
			}
		}
	],
	"variable": [
		{
			"key": "baseUrl",
			"value": "http://localhost:8080",
			"type": "string"
		},
		{
			"key": "name",
			"value": ""
		},
		{
			"key": "usersCount",
			"value": 1,
			"type": "number"
		},
		{
			"key": "catid",
			"value": 1,
			"type": "number"
		},
		{
			"key": "request_body",
			"value": ""
		},
		{
			"key": "mail",
			"value": ""
		},
		{
			"key": "response",
			"value": ""
		},
		{
			"key": "uid",
			"value": 1,
			"type": "number"
		},
		{
			"key": "vid",
			"value": 1,
			"type": "number"
		},
		{
			"key": "catname",
			"value": ""
		},
		{
			"key": "eid",
			"value": 1,
			"type": "number"
		},
		{
			"key": "compid",
			"value": 1,
			"type": "number"
		},
		{
			"key": "toCheck",
			"value": ""
		},
		{
			"key": "newDataToSet",
			"value": ""
		},
		{
			"key": "uid1",
			"value": ""
		},
		{
			"key": "reqid",
			"value": 1,
			"type": "number"
		},
		{
			"key": "catId",
			"value": ""
		},
		{
			"key": "confirmedRequests",
			"value": ""
		},
		{
			"key": "responseArr",
			"value": ""
		},
		{
			"key": "source1",
			"value": ""
		},
		{
			"key": "source2",
			"value": ""
		},
		{
			"key": "fromId",
			"value": "0"
		},
		{
			"key": "source",
			"value": ""
		}
	]
}